ansys/api/additive/VERSION
ansys/api/additive/__init__.py
ansys/api/additive/py.typed
ansys/api/additive/v0/additive_domain.proto
ansys/api/additive/v0/additive_domain_pb2.py
ansys/api/additive/v0/additive_domain_pb2.pyi
ansys/api/additive/v0/additive_domain_pb2_grpc.py
ansys/api/additive/v0/additive_domain_pb2_grpc.pyi
ansys/api/additive/v0/additive_materials.proto
ansys/api/additive/v0/additive_materials_pb2.py
ansys/api/additive/v0/additive_materials_pb2.pyi
ansys/api/additive/v0/additive_materials_pb2_grpc.py
ansys/api/additive/v0/additive_materials_pb2_grpc.pyi
ansys/api/additive/v0/additive_operations.proto
ansys/api/additive/v0/additive_operations_pb2.py
ansys/api/additive/v0/additive_operations_pb2.pyi
ansys/api/additive/v0/additive_operations_pb2_grpc.py
ansys/api/additive/v0/additive_operations_pb2_grpc.pyi
ansys/api/additive/v0/additive_server_info.proto
ansys/api/additive/v0/additive_server_info_pb2.py
ansys/api/additive/v0/additive_server_info_pb2.pyi
ansys/api/additive/v0/additive_server_info_pb2_grpc.py
ansys/api/additive/v0/additive_server_info_pb2_grpc.pyi
ansys/api/additive/v0/additive_settings.proto
ansys/api/additive/v0/additive_settings_pb2.py
ansys/api/additive/v0/additive_settings_pb2.pyi
ansys/api/additive/v0/additive_settings_pb2_grpc.py
ansys/api/additive/v0/additive_settings_pb2_grpc.pyi
ansys/api/additive/v0/additive_simulation.proto
ansys/api/additive/v0/additive_simulation_pb2.py
ansys/api/additive/v0/additive_simulation_pb2.pyi
ansys/api/additive/v0/additive_simulation_pb2_grpc.py
ansys/api/additive/v0/additive_simulation_pb2_grpc.pyi
ansys_api_additive-5.1.6.dist-info/licenses/LICENSE
google/api/annotations.proto
google/api/annotations_pb2.py
google/api/annotations_pb2.pyi
google/api/annotations_pb2_grpc.py
google/api/annotations_pb2_grpc.pyi
google/api/client.proto
google/api/client_pb2.py
google/api/client_pb2.pyi
google/api/client_pb2_grpc.py
google/api/client_pb2_grpc.pyi
google/api/http.proto
google/api/http_pb2.py
google/api/http_pb2.pyi
google/api/http_pb2_grpc.py
ansys_api_additive-5.1.6.dist-info/METADATA
ansys_api_additive-5.1.6.dist-info/WHEEL
ansys_api_additive-5.1.6.dist-info/entry_points.txt
ansys_api_additive-5.1.6.dist-info/top_level.txt
ansys_api_additive-5.1.6.dist-info/RECORD
