Metadata-Version: 2.4
Name: ansys-api-additive
Version: 5.1.6
Summary: Autogenerated python gRPC interface package for ansys-api-additive, built on 22:54:42 on 04 November 2025
Home-page: https://github.com/ansys/ansys-api-additive
Author: ANSYS, Inc.
Author-email: pyansys.core@ansys.com
Maintainer: ANSYS, Inc.
Maintainer-email: pyansys.core@ansys.com
License: MIT
Project-URL: Documentation, https://github.com/ansys/ansys-api-additive/#readme
Project-URL: Source, https://github.com/ansys/ansys-api-additive/
Project-URL: Tracker, https://github.com/ansys/ansys-api-additive/issues/
Requires-Python: >=3.8,<4
License-File: LICENSE
Requires-Dist: grpcio~=1.47
Requires-Dist: protobuf>=3.19
Dynamic: author
Dynamic: author-email
Dynamic: description
Dynamic: description-content-type
Dynamic: home-page
Dynamic: license
Dynamic: license-file
Dynamic: maintainer
Dynamic: maintainer-email
Dynamic: project-url
Dynamic: requires-dist
Dynamic: requires-python
Dynamic: summary
